odoo/addons/website_plausible/README.rst
odoo/addons/website_plausible/__init__.py
odoo/addons/website_plausible/__manifest__.py
odoo/addons/website_plausible/controllers/__init__.py
odoo/addons/website_plausible/controllers/backend.py
odoo/addons/website_plausible/i18n/es.po
odoo/addons/website_plausible/i18n/it.po
odoo/addons/website_plausible/i18n/website_plausible.pot
odoo/addons/website_plausible/models/__init__.py
odoo/addons/website_plausible/models/res_config_settings.py
odoo/addons/website_plausible/models/website.py
odoo/addons/website_plausible/readme/CONFIGURE.rst
odoo/addons/website_plausible/readme/CONTRIBUTORS.rst
odoo/addons/website_plausible/readme/DESCRIPTION.rst
odoo/addons/website_plausible/readme/ROADMAP.rst
odoo/addons/website_plausible/static/description/icon.png
odoo/addons/website_plausible/static/description/index.html
odoo/addons/website_plausible/static/src/scss/website.backend.scss
odoo/addons/website_plausible/static/src/xml/website.backend.xml
odoo/addons/website_plausible/views/templates.xml
odoo/addons/website_plausible/views/website_config_settings.xml
odoo_addon_website_plausible-15.0.1.1.1.4.dist-info/METADATA
odoo_addon_website_plausible-15.0.1.1.1.4.dist-info/WHEEL
odoo_addon_website_plausible-15.0.1.1.1.4.dist-info/top_level.txt
odoo_addon_website_plausible-15.0.1.1.1.4.dist-info/RECORD
